{"mealServiceDietInfo":[{"head":[{"list_total_count":1},{"RESULT":{"CODE":"INFO-000","MESSAGE":"정상 처리되었습니다."}}]},{"row":[{"ATPT_OFCDC_SC_CODE":"B10","ATPT_OFCDC_SC_NM":"서울특별시교육청","SD_SCHUL_CODE":"7010572","SCHUL_NM":"서울디지텍고등학교","MMEAL_SC_CODE":"2","MMEAL_SC_NM":"중식","MLSV_YMD":"20231229","MLSV_FGR":237.00,"DDISH_NM":"·감자양파국 <br/>·연근조림 (5.6.13)<br/>·열무김치 (9)<br/>·나물비빔밥&볶음고추장 (5.6)<br/>·해물완자 (2.5.6.9.12.17.18)","ORPLC_INFO":"쌀 : 국내산<br/>배추 : 국내산<br/>고춧가루 : 국내산<br/>오징어 수산가공품 : 수입<br/>비고 : ","CAL_INFO":"673.6 Kcal","NTR_INFO":"탄수화물(g) : 132.8<br/>단백질(g) : 24.3<br/>지방(g) : 4.5<br/>비타민A(R.E) : 355.9<br/>티아민(mg) : 1.0<br/>리보플라빈(mg) : 0.5<br/>비타민C(mg) : 43.9<br/>칼슘(mg) : 1356.2<br/>철분(mg) : 2.9","MLSV_FROM_YMD":"20231229","MLSV_TO_YMD":"20231229","LOAD_DTM":"20231228"}]}]}